twcollect/__init__.py
twcollect/__main__.py
twcollect/cli.py
twcollect/config.py
twcollect/streams.py
twcollect/utils.py
twcollect/drivers/__init__.py
twcollect/drivers/base.py
twcollect/drivers/local.py
twcollect-0.1.0.dist-info/LICENSE.txt
twcollect-0.1.0.dist-info/METADATA
twcollect-0.1.0.dist-info/WHEEL
twcollect-0.1.0.dist-info/top_level.txt
twcollect-0.1.0.dist-info/RECORD
