Metadata-Version: 2.1
Name: twcollect
Version: 0.1.0
Summary: Simple CLI to collect data from the Twitter stream API
Home-page: https://github.com/smassonnet/twcollect
Author: Stephane Massonnet
Author-email: stephane.massonnet@epfl.ch
License: MIT
Project-URL: Documentation, https://github.com/smassonnet/twcollect
Project-URL: Source, https://github.com/smassonnet/twcollect
Platform: any
Classifier: Development Status :: 4 - Beta
Classifier: Programming Language :: Python
Requires-Python: >=3.8
License-File: LICENSE.txt
Requires-Dist: pydantic
Requires-Dist: pyyaml
Requires-Dist: requests
Provides-Extra: testing
Requires-Dist: setuptools ; extra == 'testing'
Requires-Dist: pytest ; extra == 'testing'
Requires-Dist: pytest-cov ; extra == 'testing'
